translator/__init__.py
translator/shell.py
translator/common/__init__.py
translator/common/exception.py
translator/common/flavors.py
translator/common/images.py
translator/common/utils.py
translator/conf/__init__.py
translator/conf/config.py
translator/conf/heat_translator_logging.conf
translator/conf/translator.conf
translator/custom/__init__.py
translator/custom/hot/__init__.py
translator/hot/__init__.py
translator/hot/tosca_translator.py
translator/hot/translate_inputs.py
translator/hot/translate_node_templates.py
translator/hot/translate_outputs.py
translator/hot/syntax/__init__.py
translator/hot/syntax/hot_output.py
translator/hot/syntax/hot_parameter.py
translator/hot/syntax/hot_resource.py
translator/hot/syntax/hot_template.py
translator/hot/tests/__init__.py
translator/hot/tests/test_hot_parameter.py
translator/hot/tests/test_translate_inputs.py
translator/hot/tests/test_translate_outputs.py
translator/hot/tosca/__init__.py
translator/hot/tosca/tosca_block_storage.py
translator/hot/tosca/tosca_block_storage_attachment.py
translator/hot/tosca/tosca_cluster_policies_scaling.py
translator/hot/tosca/tosca_compute.py
translator/hot/tosca/tosca_database.py
translator/hot/tosca/tosca_dbms.py
translator/hot/tosca/tosca_floating.py
translator/hot/tosca/tosca_network_network.py
translator/hot/tosca/tosca_network_port.py
translator/hot/tosca/tosca_object_storage.py
translator/hot/tosca/tosca_policies.py
translator/hot/tosca/tosca_policies_monitoring.py
translator/hot/tosca/tosca_policies_reservation.py
translator/hot/tosca/tosca_policies_scaling.py
translator/hot/tosca/tosca_software_component.py
translator/hot/tosca/tosca_web_application.py
translator/hot/tosca/tosca_webserver.py
translator/hot/tosca/etsi_nfv/__init__.py
translator/hot/tosca/etsi_nfv/tosca_groups_nfv_placementgroup.py
translator/hot/tosca/etsi_nfv/tosca_nfv_vdu_compute.py
translator/hot/tosca/etsi_nfv/tosca_nfv_vdu_virtualblockstorage.py
translator/hot/tosca/etsi_nfv/tosca_nfv_vducp.py
heat_translator-3.3.0.dist-info/AUTHORS
heat_translator-3.3.0.dist-info/LICENSE
heat_translator-3.3.0.dist-info/METADATA
heat_translator-3.3.0.dist-info/WHEEL
heat_translator-3.3.0.dist-info/entry_points.txt
heat_translator-3.3.0.dist-info/pbr.json
heat_translator-3.3.0.dist-info/top_level.txt
heat_translator-3.3.0.dist-info/RECORD
