Metadata-Version: 2.1
Name: heat-translator
Version: 3.3.0
Summary: Tool to translate non-heat templates to Heat Orchestration Template.
Home-page: http://docs.openstack.org/heat-translator/
Author: OpenStack
Author-email: openstack-discuss@lists.openstack.org
Classifier: Environment :: OpenStack
Classifier: Intended Audience :: Information Technology
Classifier: Intended Audience :: System Administrators
Classifier: License :: OSI Approved :: Apache Software License
Classifier: Operating System :: POSIX :: Linux
Classifier: Programming Language :: Python
Classifier: Programming Language :: Python :: 3
Classifier: Programming Language :: Python :: 3.8
Classifier: Programming Language :: Python :: 3.9
Classifier: Programming Language :: Python :: 3.10
Classifier: Programming Language :: Python :: 3 :: Only
Classifier: Programming Language :: Python :: Implementation :: CPython
Requires-Python: >=3.8
License-File: LICENSE
License-File: AUTHORS
Requires-Dist: pbr >=6.0.0
Requires-Dist: cliff >=4.9.1
Requires-Dist: PyYAML >=3.13
Requires-Dist: python-dateutil >=2.9.0
Requires-Dist: tosca-parser >=2.12.0
Requires-Dist: keystoneauth1 >=5.11.0
Requires-Dist: python-novaclient >=18.9.0
Requires-Dist: python-heatclient >=4.2.0
Requires-Dist: python-glanceclient >=4.8.0
Requires-Dist: requests >=2.32.2
Requires-Dist: oslo.log >=7.1.0
